README.rst
setup.cfg
setup.py
PyFlickr.egg-info/PKG-INFO
PyFlickr.egg-info/SOURCES.txt
PyFlickr.egg-info/dependency_links.txt
PyFlickr.egg-info/requires.txt
PyFlickr.egg-info/top_level.txt
pyflickr/__init__.py
pyflickr/api.py
pyflickr/constant/constant.py
pyflickr/model/__init__.py
pyflickr/model/about.py
pyflickr/model/enum.py
pyflickr/model/photo.py
pyflickr/model/user.py