Metadata-Version: 2.1
Name: PyFlickr
Version: 1.0.0
Summary: PyFlickr - Unofficial Flickr API
Home-page: https://github.com/rf777rf777/PyFlickr
Author: SyashinChen
Author-email: rf777rf777@gmail.com
License: MIT License
Keywords: PyFlickr,flickr
Platform: UNKNOWN
Requires-Python: >=3.5
